ml_solutions/__init__.py
ml_solutions/algorithms.py
ml_solutions/neuralnet.py
ml_solutions/solutions.py
ml_solutions-0.0.3.dist-info/LICENSE
ml_solutions-0.0.3.dist-info/METADATA
ml_solutions-0.0.3.dist-info/WHEEL
ml_solutions-0.0.3.dist-info/top_level.txt
ml_solutions-0.0.3.dist-info/RECORD
