Metadata-Version: 2.1
Name: ml-solutions
Version: 0.0.3
Summary: A Python Pacakage for Ready Made Machine Learning Solutions.
Home-page: UNKNOWN
Author: Debadrito Dutta
Author-email: dipalidutta312@gmail.com
License: UNKNOWN
Keywords: ml-solutions,Machine Learning,machine learning,machine learning python,image python,image
Platform: UNKNOWN
Classifier: Programming Language :: Python :: 3
Classifier: Operating System :: Microsoft :: Windows
License-File: LICENSE
Requires-Dist: pandas
Requires-Dist: sklearn
Requires-Dist: numpy
Requires-Dist: tensorflow
Requires-Dist: opencv-python
Requires-Dist: torch
